{
    "success": true,
    "data": {
        "created": "timestamp",
        "title": "Front End Developer",
        "company": "Apple",
        "progress": "Started Application",
        "contact": [{
            "name": "Mr.Jobs",
            "email": "mrjobs@apple.com",
            "phone": 17232322456
        }],
        "note": [{
            "created": "timestamp",
            "input": "Just applied today, waiting to hear back in two weeks"
        }, {
            "created": "timestamp",
            "input": "Saw this guy again at the meetup, he said his daughter was turning 2"
        }],
        "link": "www.apple.com"
    }
}